pyonfireapi/__init__.py
pyonfireapi/client.py
pyonfireapi/constants.py
pyonfireapi/exception.py
pyonfireapi/utils.py
pyonfireapi/api/__init__.py
pyonfireapi/api/account.py
pyonfireapi/api/accounting.py
pyonfireapi/api/base.py
pyonfireapi/api/dedicated.py
pyonfireapi/api/domain.py
pyonfireapi/api/vm.py
pyonfireapi-0.0.4.dist-info/LICENSE
pyonfireapi-0.0.4.dist-info/METADATA
pyonfireapi-0.0.4.dist-info/WHEEL
pyonfireapi-0.0.4.dist-info/top_level.txt
pyonfireapi-0.0.4.dist-info/RECORD
