Metadata-Version: 2.1
Name: pyonfireapi
Version: 0.0.4
Summary: Unofficial API client for the FireAPI from 24fire GmbH.
Author-email: Cownex <justin@cavening.de>
Project-URL: Homepage, https://github.com/Cownex/py-fireapi
Project-URL: Issues, https://github.com/Cownex/py-fireapi
Classifier: Programming Language :: Python :: 3
Classifier: License :: OSI Approved :: MIT License
Classifier: Operating System :: OS Independent
Requires-Python: >=3.8
License-File: LICENSE
